vcf_parser.py
vcf2csv-1.0.0.dist-info/LICENSE
vcf2csv-1.0.0.dist-info/METADATA
vcf2csv-1.0.0.dist-info/WHEEL
vcf2csv-1.0.0.dist-info/entry_points.txt
vcf2csv-1.0.0.dist-info/top_level.txt
vcf2csv-1.0.0.dist-info/RECORD
